autoqa-1.0.0.dist-info/licenses/LICENSE
autoqa-1.0.0.dist-info/licenses/LICENSE.md
cli/main.py
cli/py.typed
cli/test_main.py
common/agent.py
common/llm.py
common/py.typed
common/slack.py
common/test_agent.py
common/test_slack.py
common/test_utils.py
common/utils.py
graph/prompt_node.py
graph/py.typed
graph/test_prompt_node.py
graph/test_workflow.py
graph/workflow.py
autoqa-1.0.0.dist-info/METADATA
autoqa-1.0.0.dist-info/WHEEL
autoqa-1.0.0.dist-info/entry_points.txt
autoqa-1.0.0.dist-info/top_level.txt
autoqa-1.0.0.dist-info/RECORD
