Metadata-Version: 2.4
Name: autoqa
Version: 1.0.0
Summary: AI-powered automated test generation, validation, and repair.
Author-email: Shelton Wilson <sheltonwlsn@gmail.com>
Requires-Python: >=3.8
License-File: LICENSE
License-File: LICENSE.md
Requires-Dist: click>=8.2.1
Requires-Dist: python-dotenv
Requires-Dist: httpx
Requires-Dist: langchain>=0.3.26
Requires-Dist: langchain-anthropic>=0.3.17
Requires-Dist: langchain-openai>=0.3.26
Requires-Dist: langchain-google-vertexai>=2.0.27
Requires-Dist: langgraph>=0.5.1
Requires-Dist: pydantic>=2.11.7
Requires-Dist: rich
Requires-Dist: toml
Provides-Extra: dev
Requires-Dist: pytest; extra == "dev"
Requires-Dist: black; extra == "dev"
Dynamic: license-file
